simple_background_remover/__init__.py
simple_background_remover/color_helper.py
simple_background_remover/logger.py
simple_background_remover/simple_background_remover.py
simple_background_remover-1.0.1.dist-info/METADATA
simple_background_remover-1.0.1.dist-info/WHEEL
simple_background_remover-1.0.1.dist-info/licenses/LICENSE
simple_background_remover-1.0.1.dist-info/RECORD
