Metadata-Version: 2.3
Name: simple_background_remover
Version: 1.0.1
Summary: A quick and dirty background remover for simple images with solid(ish) background colors.
Project-URL: Homepage, https://github.com/oversizedcanoe/simple_background_remover 
Author: oversizedcanoe
License-File: LICENSE
Classifier: License :: OSI Approved :: MIT License
Classifier: Operating System :: OS Independent
Classifier: Programming Language :: Python :: 3
Requires-Python: >=3.8
Requires-Dist: pillow>=10.2.0
